{
    "id":  "2",
    "name":  "SACRIFICE TEE",
    "slug":  "sacrifice-tee",
    "price":  89,
    "category":  "t-shirts",
    "images":  [
                   {
                       "src":  "https://images.pexels.com/photos/5632402/pexels-photo-5632402.jpeg?auto=compress\u0026cs=tinysrgb\u0026w=800"
                   },
                   {
                       "src":  "https://images.pexels.com/photos/17854971/pexels-photo-17854971.jpeg?auto=compress\u0026cs=tinysrgb\u0026w=800"
                   },
                   {
                       "src":  "https://images.pexels.com/photos/1043473/pexels-photo-1043473.jpeg?auto=compress\u0026cs=tinysrgb\u0026w=800"
                   }
               ],
    "sizes":  [
                  {
                      "name":  "XS",
                      "available":  true
                  },
                  {
                      "name":  "S",
                      "available":  true
                  },
                  {
                      "name":  "M",
                      "available":  true
                  },
                  {
                      "name":  "L",
                      "available":  true
                  },
                  {
                      "name":  "XL",
                      "available":  true
                  },
                  {
                      "name":  "XXL",
                      "available":  true
                  }
              ],
    "inStock":  true,
    "isFeatured":  true,
    "isBestseller":  true,
    "rating":  4.8,
    "shortDescription":  "Р В¤РЎС“РЎвЂљР В±Р С•Р В»Р С”Р В° Р В· РЎРЏР С—Р С•Р Р…РЎРѓРЎРЉР С”Р С•РЎвЂ” Р В±Р В°Р Р†Р С•Р Р†Р Р…Р С‘ Р В· Р С–РЎР‚Р В°РЎвЂћРЎвЂ“РЎвЂЎР Р…Р С‘Р С Р С—РЎР‚Р С‘Р Р…РЎвЂљР С•Р С РЎР‚РЎС“РЎвЂЎР Р…Р С•РЎвЂ” РЎР‚Р С•Р В±Р С•РЎвЂљР С‘",
    "description":  "Sacrifice Tee Р С—РЎР‚Р ВµР Т‘РЎРѓРЎвЂљР В°Р Р†Р В»РЎРЏРЎвЂќ Р Р…Р В°РЎв‚¬ Р С”РЎС“Р В»РЎРЉРЎвЂљР С•Р Р†Р С‘Р в„– Р С—РЎР‚Р С‘Р Р…РЎвЂљ Р Р…Р В° Р С—РЎР‚Р ВµР СРЎвЂ“Р В°Р В»РЎРЉР Р…РЎвЂ“Р в„– РЎРЏР С—Р С•Р Р…РЎРѓРЎРЉР С”РЎвЂ“Р в„– Р В±Р В°Р Р†Р С•Р Р†Р Р…РЎвЂ“. Р С™Р С•Р В¶Р ВµР Р… Р Р†Р С‘РЎР‚РЎвЂ“Р В± Р С—РЎР‚Р С•РЎвЂ¦Р С•Р Т‘Р С‘РЎвЂљРЎРЉ РЎС“Р Р…РЎвЂ“Р С”Р В°Р В»РЎРЉР Р…Р С‘Р в„– Р С—РЎР‚Р С•РЎвЂ Р ВµРЎРѓ Р С—РЎР‚Р В°Р Р…Р Р…РЎРЏ, РЎвЂ°Р С• Р Т‘Р В°РЎвЂќ Р В»Р ВµР Т‘РЎРЉ Р С—Р С•Р СРЎвЂ“РЎвЂљР Р…РЎвЂ“ Р Р†Р В°РЎР‚РЎвЂ“Р В°РЎвЂ РЎвЂ“РЎвЂ” РЎвЂљР В° РЎР‚Р С•Р В±Р С‘РЎвЂљРЎРЉ Р С”Р С•Р В¶Р Р…РЎС“ РЎвЂћРЎС“РЎвЂљР В±Р С•Р В»Р С”РЎС“ РЎвЂќР Т‘Р С‘Р Р…Р С•РЎР‹ РЎС“ РЎРѓР Р†Р С•РЎвЂќР СРЎС“ РЎР‚Р С•Р Т‘РЎвЂ“. Р вЂ™РЎвЂ“Р В»РЎРЉР Р…Р С‘Р в„– Р С”РЎР‚РЎвЂ“Р в„– РЎвЂљР В° Р С—Р С•РЎРѓР С‘Р В»Р ВµР Р…Р В° Р С–Р С•РЎР‚Р В»Р С•Р Р†Р С‘Р Р…Р В° Р В·Р В°Р В±Р ВµР В·Р С—Р ВµРЎвЂЎРЎС“РЎР‹РЎвЂљРЎРЉ РЎвЂљРЎР‚Р С‘Р Р†Р В°Р В»Р С‘Р в„– Р С”Р С•Р СРЎвЂћР С•РЎР‚РЎвЂљ РЎвЂ“ Р СРЎвЂ“РЎвЂ Р Р…РЎвЂ“РЎРѓРЎвЂљРЎРЉ.",
    "details":  [
                    "Р Р‡Р С—Р С•Р Р…РЎРѓРЎРЉР С”Р В° Р В±Р В°Р Р†Р С•Р Р†Р Р…Р В° 180 Р С–/Р СР’Р†",
                    "Р Р€Р Р…РЎвЂ“Р С”Р В°Р В»РЎРЉР Р…Р В° Р С•Р В±РЎР‚Р С•Р В±Р С”Р В° stone-wash",
                    "Р вЂ™РЎвЂ“Р В»РЎРЉР Р…Р С‘Р в„– Р С”РЎР‚РЎвЂ“Р в„–",
                    "Р СџР С•РЎРѓР С‘Р В»Р ВµР Р…Р В° Р С–Р С•РЎР‚Р В»Р С•Р Р†Р С‘Р Р…Р В°",
                    "Р РЃР С•Р Р†Р С”Р С•Р С–РЎР‚Р В°РЎвЂћРЎвЂ“РЎвЂЎР Р…Р С‘Р в„– Р С—РЎР‚Р С‘Р Р…РЎвЂљ"
                ],
    "reviews":  [
                    {
                        "id":  "2",
                        "author":  "Elena K.",
                        "rating":  5,
                        "title":  "Р вЂ™Р В°РЎР‚РЎвЂљРЎС“РЎвЂќ Р С”Р С•Р В¶Р Р…Р С•РЎвЂ” Р С”Р С•Р С—РЎвЂ“Р в„–Р С”Р С‘",
                        "content":  "Р РЋРЎС“Р СР Р…РЎвЂ“Р Р†Р В°Р В»Р В°РЎРѓРЎРЏ РЎвЂ°Р С•Р Т‘Р С• РЎвЂ РЎвЂ“Р Р…Р С‘, Р В°Р В»Р Вµ Р Р† Р СР С•Р СР ВµР Р…РЎвЂљ, Р С”Р С•Р В»Р С‘ Р С•Р Т‘РЎРЏР С–Р В»Р В°, Р Р†РЎРѓР Вµ Р В·РЎР‚Р С•Р В·РЎС“Р СРЎвЂ“Р В»Р В°. Р СљР В°Р в„–РЎРѓРЎвЂљР ВµРЎР‚Р Р…РЎвЂ“РЎРѓРЎвЂљРЎРЉ Р Р†Р С‘Р С”Р С•Р Р…Р В°Р Р…Р Р…РЎРЏ Р Р…Р В° РЎвЂ“Р Р…РЎв‚¬Р С•Р СРЎС“ РЎР‚РЎвЂ“Р Р†Р Р…РЎвЂ“. Р вЂќРЎС“Р В¶Р Вµ РЎР‚Р ВµР С”Р С•Р СР ВµР Р…Р Т‘РЎС“РЎР‹.",
                        "date":  "2024-01-10",
                        "verified":  true
                    }
                ]
}